mistfit/__init__.py
mistfit/cli.py
mistfit/core.py
mistfit-0.0.1.dist-info/METADATA
mistfit-0.0.1.dist-info/WHEEL
mistfit-0.0.1.dist-info/entry_points.txt
mistfit-0.0.1.dist-info/top_level.txt
mistfit-0.0.1.dist-info/RECORD
