Metadata-Version: 2.4
Name: mistfit
Version: 0.0.1
Summary: Fit MIST models using MiniMINT with dynesty nested sampling (photometry + spectroscopic constraints).
Author: Manuel Cavieres
Project-URL: Homepage, https://github.com/mncavieres/mistfit
Project-URL: Issues, https://github.com/mncavieres/mistfit/issues
Keywords: MIST,stellar,astrophysics,dynesty,minimint,isochrones
Classifier: Programming Language :: Python :: 3
Classifier: Operating System :: OS Independent
Classifier: Intended Audience :: Science/Research
Classifier: Topic :: Scientific/Engineering :: Astronomy
Requires-Python: >=3.9
Requires-Dist: numpy>=1.23
Requires-Dist: scipy>=1.10
Requires-Dist: astropy>=5
Requires-Dist: dynesty>=2.1
Requires-Dist: minimint>=0.5
Requires-Dist: matplotlib>=3.6
Requires-Dist: tqdm>=4.64
Provides-Extra: dev
Requires-Dist: pytest; extra == "dev"
Requires-Dist: pytest-cov; extra == "dev"
Requires-Dist: ruff; extra == "dev"
Requires-Dist: mypy; extra == "dev"
Requires-Dist: build; extra == "dev"
Requires-Dist: twine; extra == "dev"
Provides-Extra: plot
Requires-Dist: corner>=2.2; extra == "plot"
